DeltaKG/__init__.py
DeltaKG/src/__init__.py
DeltaKG/src/data/__init__.py
DeltaKG/src/data/data_module.py
DeltaKG/src/data/processor.py
DeltaKG/src/models/__init__.py
DeltaKG/src/models/modeling_bert.py
DeltaKG/src/models/models.py
DeltaKG/src/models/optimization.py
DeltaKG/src/models/trainer.py
DeltaKG-0.0.6.dist-info/LICENSE.txt
DeltaKG-0.0.6.dist-info/METADATA
DeltaKG-0.0.6.dist-info/WHEEL
DeltaKG-0.0.6.dist-info/top_level.txt
DeltaKG-0.0.6.dist-info/RECORD
