Metadata-Version: 2.1
Name: DeltaKG
Version: 0.0.6
Summary: A Library for Dynamically Editing PLMs-Based Knowledge Graph Embeddings.
Home-page: https://github.com/zjunlp/PromptKG/tree/main/deltaKG
Author: Bozhong Tian
Author-email: tbozhong@zju.edu.cn
Keywords: knowledge graph embedding edit
Classifier: Programming Language :: Python :: 3
Classifier: License :: OSI Approved :: MIT License
Classifier: Operating System :: OS Independent
Requires-Python: >=3.6
License-File: LICENSE.txt
